wordsegment_rs-0.2.0.dist-info/METADATA
wordsegment_rs-0.2.0.dist-info/WHEEL
wordsegment_rs-0.2.0.dist-info/license_files/LICENSE
wordsegment_rs/bigrams.txt
wordsegment_rs/unigrams.txt
wordsegment_rs/words.txt
wordsegment_rs/__init__.py
wordsegment_rs/__main__.py
wordsegment_rs/wordsegment_rs.cp310-win_amd64.pyd
wordsegment_rs-0.2.0.dist-info/RECORD
